baiji/__init__.py
baiji/serialization/__init__.py
baiji/serialization/csv.py
baiji/serialization/json.py
baiji/serialization/pickle.py
baiji/serialization/test_csv.py
baiji/serialization/test_json.py
baiji/serialization/test_yaml.py
baiji/serialization/yaml.py
baiji/serialization/util/__init__.py
baiji/serialization/util/importlib.py
baiji/serialization/util/openlib.py
baiji_serialization-2.1.0.dist-info/DESCRIPTION.rst
baiji_serialization-2.1.0.dist-info/METADATA
baiji_serialization-2.1.0.dist-info/RECORD
baiji_serialization-2.1.0.dist-info/WHEEL
baiji_serialization-2.1.0.dist-info/metadata.json
baiji_serialization-2.1.0.dist-info/top_level.txt
