Metadata-Version: 2.0
Name: baiji-serialization
Version: 2.1.0
Summary: Read and write common file formats to Amazon S3 and local files
Home-page: https://github.com/bodylabs/baiji-serialization
Author: Body Labs
Author-email: alex@bodylabs.com, paul.melnikow@bodylabs.com
License: Apache
Platform: UNKNOWN
Classifier: Development Status :: 3 - Alpha
Classifier: Intended Audience :: Developers
Classifier: License :: OSI Approved :: MIT License
Classifier: Operating System :: OS Independent
Classifier: Programming Language :: Python
Requires-Dist: baiji
Requires-Dist: pyyaml (>=3.11)
Requires-Dist: simplejson (>=3.8.2)
